<?xml version="1.0" encoding="utf-8" ?><dwsync><file name="EmailListEntry.php" server="ftp40.bravehost.com" local="3414943083" remote="12006210433" /><file name="EmailListFeed.php" server="ftp40.bravehost.com" local="3414943083" remote="12006210433" /><file name="EmailListQuery.php" server="ftp40.bravehost.com" local="3414943083" remote="12006210434" /><file name="EmailListRecipientEntry.php" server="ftp40.bravehost.com" local="3414943083" remote="12006210434" /><file name="EmailListRecipientFeed.php" server="ftp40.bravehost.com" local="3414943083" remote="12006210434" /><file name="EmailListRecipientQuery.php" server="ftp40.bravehost.com" local="3414943083" remote="12006210434" /><file name="Error.php" server="ftp40.bravehost.com" local="3414943083" remote="12006210435" /><file name="GroupEntry.php" server="ftp40.bravehost.com" local="3414943083" remote="12006210438" /><file name="GroupFeed.php" server="ftp40.bravehost.com" local="3414943083" remote="12006210438" /><file name="GroupQuery.php" server="ftp40.bravehost.com" local="3414943083" remote="12006210438" /><file name="MemberEntry.php" server="ftp40.bravehost.com" local="3414943083" remote="12006210439" /><file name="MemberFeed.php" server="ftp40.bravehost.com" local="3414943083" remote="12006210439" /><file name="MemberQuery.php" server="ftp40.bravehost.com" local="3414943083" remote="12006210439" /><file name="NicknameEntry.php" server="ftp40.bravehost.com" local="3414943083" remote="12006210440" /><file name="NicknameFeed.php" server="ftp40.bravehost.com" local="3414943083" remote="12006210440" /><file name="NicknameQuery.php" server="ftp40.bravehost.com" local="3414943083" remote="12006210440" /><file name="OwnerEntry.php" server="ftp40.bravehost.com" local="3414943083" remote="12006210441" /><file name="OwnerFeed.php" server="ftp40.bravehost.com" local="3414943083" remote="12006210441" /><file name="OwnerQuery.php" server="ftp40.bravehost.com" local="3414943083" remote="12006210442" /><file name="Query.php" server="ftp40.bravehost.com" local="3414943083" remote="12006210442" /><file name="ServiceException.php" server="ftp40.bravehost.com" local="3414943083" remote="12006210442" /><file name="UserEntry.php" server="ftp40.bravehost.com" local="3414943083" remote="12006210442" /><file name="UserFeed.php" server="ftp40.bravehost.com" local="3414943083" remote="12006210443" /><file name="UserQuery.php" server="ftp40.bravehost.com" local="3414943083" remote="12006210443" /></dwsync>